README.rst
setup.py
quasiquotes/__init__.py
quasiquotes/quasiquoter.py
quasiquotes.egg-info/PKG-INFO
quasiquotes.egg-info/SOURCES.txt
quasiquotes.egg-info/dependency_links.txt
quasiquotes.egg-info/top_level.txt
quasiquotes/c/__init__.py
quasiquotes/c/__main__.py
quasiquotes/c/_loader.c
quasiquotes/codec/__init__.py
quasiquotes/codec/register.py
quasiquotes/codec/search.py
quasiquotes/codec/tokenizer.py
quasiquotes/utils/__init__.py
quasiquotes/utils/_traceback.py
quasiquotes/utils/instance.py
quasiquotes/utils/shell.py