Metadata-Version: 1.1
Name: quasiquotes
Version: 0.2.0
Summary: Quasiquotation in python
Home-page: https://github.com/llllllllll/quasiquotes
Author: Joe Jevnik
Author-email: joejev@gmail.com
License: GPL-2
Platform: UNKNOWN
Classifier: Development Status :: 3 - Alpha
Classifier: License :: OSI Approved :: GNU General Public License v2 (GPLv2)
Classifier: Natural Language :: English
Classifier: Programming Language :: Python :: 3.4
Classifier: Programming Language :: Python :: 3 :: Only
Classifier: Topic :: Software Development :: Pre-processors
